{
  "version": "6.3.1",
  "flags": {},
  "shapes": [
    {
      "label": "Face",
      "points": [
        [
          279.8837209302325,
          2.209302325581401
        ],
        [
          504.30232558139534,
          368.48837209302326
        ]
      ],
      "group_id": null,
      "description": "",
      "shape_type": "rectangle",
      "flags": {},
      "mask": null
    }
  ],
  "imagePath": "..\\df568647-7389-11f1-8c6c-26b2b98917c5.jpg",
  "imageData": null,
  "imageHeight": 480,
  "imageWidth": 640
}